{
    "subscriptions": {
        "botperks": [
            [
                "Access to /monthly & /weekly",
                "All 5-second cooldowns are 1 second",
                "30-minute cooldown on airdrops",
                "Premium Achievement + Badge",
                "Buy up to 15 plots instead of 9",
                "Get a lucky wheel spin with /daily",
                "Increased /daily limit to 200",
                "Ability to open loot boxes",
                "All votes count double",
                "Increased betting limit (10.000) in all games",
                "Ability to change profile color"
            ],
            [
                "All perks from Supporter (only for you)",
                "You can activate all the perks for 1 server",
                "Apply to everyone in the server",
                "Change airdrop cooldown",
                "All 5-second cooldowns are 3 seconds",
                "Ability to host own airdrops (like giveaways)",
                "SOON: Ability to change embed colors",
                "SOON: Ability to change coin emote"
            ],
            [
                "All perks from Supporter (only for you)",
                "You can activate all the perks for 3 servers",
                "Apply to everyone in the server",
                "Change airdrop cooldown",
                "All 5-second cooldowns are 3 seconds",
                "Ability to host own airdrops (like giveaways)",
                "SOON: Ability to change embed colors",
                "SOON: Ability to change coin emote"
            ]
        ],
        "serverperks": [
            [
                "Premium role",
                "Access to an exclusive channel",
                "Ability to use Coinz Beta"
            ],
            [
                "Premium role",
                "Access to an exclusive channel",
                "Ability to use Coinz Beta",
                "Promote your server in #premium"
            ],
            [
                "Premium role",
                "Access to an exclusive channel",
                "Ability to use Coinz Beta",
                "Promote your server in #premium"
            ]
        ]
    },
    "lootboxes": {
        "tools": {
            "name": "Tools Loot Box",
            "price": 70,
            "loot": [
                {
                    "name": "Coins",
                    "amount": 320,
                    "emoteId": "987800268223709254"
                },
                {
                    "name": "Tickets",
                    "amount": 20,
                    "emoteId": "1032669959161122976"
                },
                {
                    "name": "Shovel",
                    "amount": 2,
                    "emoteId": "956861323352883230"
                },
                {
                    "name": "Fishing Rod",
                    "amount": 2,
                    "emoteId": "956861323617107968"
                },
                {
                    "name": "Hunting Rifle",
                    "amount": 1,
                    "emoteId": "987701755770994718"
                },
                {
                    "name": "Axe",
                    "amount": 3,
                    "emoteId": "1013473902778908694"
                },
                {
                    "name": "Bag",
                    "amount": 4,
                    "emoteId": "1013473900123926618"
                }
            ]
        },
        "random": {
            "name": "Random Loot Box",
            "price": 110,
            "loot": [
                {
                    "name": "Coins",
                    "amount": 600,
                    "emoteId": "987800268223709254"
                },
                {
                    "name": "Tickets",
                    "amount": 50,
                    "emoteId": "1032669959161122976"
                },
                {
                    "name": "Shoe",
                    "amount": 10,
                    "emoteId": "956916922572763166"
                },
                {
                    "name": "Playstation",
                    "amount": 1,
                    "emoteId": "956917165250990091"
                },
                {
                    "name": "Book",
                    "amount": 35,
                    "emoteId": "956916922837000293"
                },
                {
                    "name": "Tree",
                    "amount": 3,
                    "emoteId": "956916922623094834"
                },
                {
                    "name": "Lamp",
                    "amount": 6,
                    "emoteId": "956917165959815238"
                },
                {
                    "name": "Pocket Watch",
                    "amount": 5,
                    "emoteId": "1003948943027220520"
                },
                {
                    "name": "Television",
                    "amount": 2,
                    "emoteId": "1003948945359245323"
                },
                {
                    "name": "Smartphone",
                    "amount": 1,
                    "emoteId": "1013474375275663530"
                },
                {
                    "name": "Crown",
                    "amount": 1,
                    "emoteId": "956919874494533642"
                }
            ]
        },
        "pirates": {
            "name": "Pirates Loot Box",
            "price": 180,
            "loot": [
                {
                    "name": "Coins",
                    "amount": 750,
                    "emoteId": "987800268223709254"
                },
                {
                    "name": "Tickets",
                    "amount": 70,
                    "emoteId": "1032669959161122976"
                },
                {
                    "name": "Gold",
                    "amount": 1,
                    "emoteId": "956920061191393280"
                },
                {
                    "name": "Oil",
                    "amount": 1,
                    "emoteId": "956920061178835004"
                },
                {
                    "name": "Christmas Tree",
                    "amount": 1,
                    "emoteId": "956919874653933568"
                },
                {
                    "name": "Toilet Paper",
                    "amount": 1,
                    "emoteId": "1003949881746006066"
                },
                {
                    "name": "Ring",
                    "amount": 1,
                    "emoteId": "1003949880466751508"
                },
                {
                    "name": "Book",
                    "amount": 40,
                    "emoteId": "956916922837000293"
                },
                {
                    "name": "Potato",
                    "amount": 30,
                    "emoteId": "956643928013152306"
                },
                {
                    "name": "Playstation",
                    "amount": 1,
                    "emoteId": "956917165250990091"
                },
                {
                    "name": "Trash",
                    "amount": 23,
                    "emoteId": "956916922610507777"
                }
            ]
        }
    }
}